hiouk/Hiouk.py
hiouk/__init__.py
Hiouk-1.0.0.dist-info/METADATA
Hiouk-1.0.0.dist-info/WHEEL
Hiouk-1.0.0.dist-info/top_level.txt
Hiouk-1.0.0.dist-info/RECORD
